ichain/__init__.py
ichain-0.1.3.dist-info/LICENSE
ichain-0.1.3.dist-info/METADATA
ichain-0.1.3.dist-info/WHEEL
ichain-0.1.3.dist-info/RECORD
